PokE_Trade/API.py
PokE_Trade/ItemID.csv
PokE_Trade/PokE_Trade.py
PokE_Trade/Widgets.py
PokE_Trade/__init__.py
PokE_Trade/bg.png
PokE_Trade/icon.ico
PokE_Trade-1.0.7.dist-info/METADATA
PokE_Trade-1.0.7.dist-info/WHEEL
PokE_Trade-1.0.7.dist-info/top_level.txt
PokE_Trade-1.0.7.dist-info/RECORD
